fwcl/__init__.py
fwcl/api_params.py
fwcl/api_results.py
fwcl/base_facade.py
fwcl/fwcl.py
fwcl/login_facade.py
fwcl-0.8.1.dist-info/LICENSE
fwcl-0.8.1.dist-info/METADATA
fwcl-0.8.1.dist-info/WHEEL
fwcl-0.8.1.dist-info/top_level.txt
fwcl-0.8.1.dist-info/RECORD
